polog/__init__.py
polog/config.py
polog/errors.py
polog/field.py
polog/forbid.py
polog/unlog.py
polog/core/__init__.py
polog/core/levels.py
polog/core/log_item.py
polog/core/registering_functions.py
polog/core/settings_store.py
polog/core/worker.py
polog/core/writer.py
polog/core/engine/__init__.py
polog/core/engine/engine.py
polog/core/engine/real_engines/__init__.py
polog/core/engine/real_engines/abstract.py
polog/core/engine/real_engines/fabric.py
polog/core/engine/real_engines/multithreaded/__init__.py
polog/core/engine/real_engines/multithreaded/engine.py
polog/core/engine/real_engines/multithreaded/pool.py
polog/core/engine/real_engines/multithreaded/worker.py
polog/core/engine/real_engines/singlethreaded/__init__.py
polog/core/engine/real_engines/singlethreaded/engine.py
polog/core/stores/__init__.py
polog/core/stores/fields.py
polog/core/stores/handlers.py
polog/core/stores/levels.py
polog/core/stores/registering_functions.py
polog/core/stores/settings/__init__.py
polog/core/stores/settings/setting_point.py
polog/core/stores/settings/settings_store.py
polog/core/stores/settings/actions/__init__.py
polog/core/stores/settings/actions/decorator.py
polog/core/stores/settings/actions/fields_intersection.py
polog/core/stores/settings/actions/integration_with_logging.py
polog/core/stores/settings/actions/reload_engine.py
polog/core/stores/settings/actions/set_log_as_built_in.py
polog/core/utils/__init__.py
polog/core/utils/cut_traceback.py
polog/core/utils/exception_escaping.py
polog/core/utils/exception_is_suppressed.py
polog/core/utils/exception_to_dict.py
polog/core/utils/get_errors_level.py
polog/core/utils/get_traceback.py
polog/core/utils/is_handler.py
polog/core/utils/is_json.py
polog/core/utils/name_manager.py
polog/core/utils/not_none_to_dict.py
polog/core/utils/pony_names_generator.py
polog/core/utils/read_only_singleton.py
polog/core/utils/reload_engine.py
polog/core/utils/signature_matcher.py
polog/core/utils/time_limit.py
polog-0.0.17.dist-info/LICENSE
polog-0.0.17.dist-info/METADATA
polog-0.0.17.dist-info/WHEEL
polog-0.0.17.dist-info/top_level.txt
polog-0.0.17.dist-info/RECORD
