Metadata-Version: 2.1
Name: polog
Version: 0.0.17
Summary: The new generation logger
Home-page: https://github.com/pomponchik/polog
Author: Evgeniy Blinov
Author-email: zheni-b@yandex.ru
License: UNKNOWN
Platform: UNKNOWN
Classifier: Programming Language :: Python :: 3.8
Classifier: License :: OSI Approved :: MIT License
